{
	"translations": {
		"de": {
			"Markdown convert to HTML": "Markdown in HTML konvertieren",

			"__function__": "CheckConfiguration",
			"Webhook is already used": "Webhook wird bereits verwendet",
			"Markdown variable of item {$idx} must be type string": "Markdown-Variable des Eintrags {$idx} muss vom Typ String sein",
			"Markdown variable of item {$idx} isn't specified": "Markdown-Variable des Eintrags {$idx} ist nicht spezifiziert",
			"HTML variable of item {$idx} must have variable profile \"~HTMLBox\"": "HTML-Variable des Eintrags {$idx} muss das Variablenprofil \"~HTMLBox\" haben",

			"__properties__": "",
			"Disable instance": "Instanz deaktivieren",

			"Access to webhook": "Zugriff auf Webhook",
			"Name": "Bezeichnung",
			"User": "Benutzerkennung",
			"Password": "Kennwort",
			"Markdown variable": "Markdown-Variable",
			"HTML variable": "HTML-Variable",
			"Title": "Titel",
			"Editable items": "Bearbeitbare Elemente",

			"Defaults for the converter options": "Standardwerte für die Optionen des Konverters",
			"Parser option \"SafeMode\"": "Parser-Option \"SafeMode\"",
			"Parser option \"MarkupEscaped\"": "Parser-Option \"MarkupEscaped\"",
			"Parser option \"BreaksEnabled\"": "Parser-Option \"BreaksEnabled\"",
			"Parser option \"UrlsLinked\"": "Parser-Option \"UrlsLinked\"",
			"Parser option \"Inline\"": "Parser-Option \"Inline\"",
			"Add HTML code as wrapper": "HTML-Code als Wrapper hinzufügen",

			"Editor configuration": "Editor-Konfiguration",
			"Editor option \"spellChecker\"": "Editor-Option \"spellChecker\"",
			"Editor option \"codeSyntaxHighlighting\"": "Editor-Option \"codeSyntaxHighlighting\"",

			"__actions__": "",
			"Open editor": "Editor öffnen",

			"__end__": ""
		}
	}
}
